{"increment":13,"list":{"1":{"update_at":"2022-02-14T23:45:25.7463703+03:00","created_at":"2022-02-14T23:45:25.7463703+03:00","display_name":"test","email":"test@gmail.com"},"10":{"update_at":"2022-02-15T10:19:04.9498374+03:00","created_at":"2022-02-15T10:19:04.9498374+03:00","display_name":"test","email":"test@gmail.com"},"11":{"update_at":"2022-02-15T10:19:04.955488+03:00","created_at":"2022-02-15T10:19:04.955488+03:00","display_name":"test","email":"test@gmail.com"},"12":{"update_at":"2022-02-15T10:19:04.9617835+03:00","created_at":"2022-02-15T10:19:04.9617835+03:00","display_name":"test","email":"test@gmail.com"},"2":{"update_at":"2022-02-15T09:47:17.8839591+03:00","created_at":"2022-02-15T09:47:17.8839591+03:00","display_name":"test","email":"test@gmail.com"},"3":{"update_at":"2022-02-15T09:47:17.887094+03:00","created_at":"2022-02-15T09:47:17.887094+03:00","display_name":"test","email":"test@gmail.com"},"4":{"update_at":"2022-02-15T09:47:17.8917771+03:00","created_at":"2022-02-15T09:47:17.8917771+03:00","display_name":"test","email":"test@gmail.com"},"6":{"update_at":"2022-02-15T09:53:26.302657+03:00","created_at":"2022-02-15T09:53:26.302657+03:00","display_name":"test","email":"test@gmail.com"},"7":{"update_at":"2022-02-15T09:53:26.3062923+03:00","created_at":"2022-02-15T09:53:26.3062923+03:00","display_name":"test","email":"test@gmail.com"},"8":{"update_at":"2022-02-15T09:53:26.3105467+03:00","created_at":"2022-02-15T09:53:26.3105467+03:00","display_name":"test","email":"test@gmail.com"}}}